sophia/__init__.py
sophia/sophia.py
sophia_optimizer-0.2.5.dist-info/LICENSE
sophia_optimizer-0.2.5.dist-info/WHEEL
sophia_optimizer-0.2.5.dist-info/METADATA
sophia_optimizer-0.2.5.dist-info/RECORD
